vdirsyncer/__init__.py
vdirsyncer/__main__.py
vdirsyncer/exceptions.py
vdirsyncer/http.py
vdirsyncer/metasync.py
vdirsyncer/repair.py
vdirsyncer/utils.py
vdirsyncer/version.py
vdirsyncer/vobject.py
vdirsyncer/cli/__init__.py
vdirsyncer/cli/config.py
vdirsyncer/cli/discover.py
vdirsyncer/cli/fetchparams.py
vdirsyncer/cli/tasks.py
vdirsyncer/cli/utils.py
vdirsyncer/storage/__init__.py
vdirsyncer/storage/base.py
vdirsyncer/storage/dav.py
vdirsyncer/storage/filesystem.py
vdirsyncer/storage/google.py
vdirsyncer/storage/google_helpers.py
vdirsyncer/storage/http.py
vdirsyncer/storage/memory.py
vdirsyncer/storage/singlefile.py
vdirsyncer/sync/__init__.py
vdirsyncer/sync/exceptions.py
vdirsyncer/sync/status.py
vdirsyncer-0.20.0.dist-info/licenses/LICENSE
vdirsyncer-0.20.0.dist-info/METADATA
vdirsyncer-0.20.0.dist-info/WHEEL
vdirsyncer-0.20.0.dist-info/entry_points.txt
vdirsyncer-0.20.0.dist-info/top_level.txt
vdirsyncer-0.20.0.dist-info/RECORD
