Metadata-Version: 2.4
Name: vdirsyncer
Version: 0.20.0
Summary: Synchronize calendars and contacts
Author-email: Markus Unterwaditzer <markus@unterwaditzer.net>
License-Expression: BSD-3-Clause
Keywords: todo,task,icalendar,cli
Classifier: Development Status :: 4 - Beta
Classifier: Environment :: Console
Classifier: Operating System :: POSIX
Classifier: Programming Language :: Python :: 3
Classifier: Programming Language :: Python :: 3.10
Classifier: Programming Language :: Python :: 3.11
Classifier: Programming Language :: Python :: 3.12
Classifier: Programming Language :: Python :: 3.13
Classifier: Programming Language :: Python :: 3.8
Classifier: Programming Language :: Python :: 3.9
Classifier: Topic :: Internet
Classifier: Topic :: Office/Business :: Scheduling
Classifier: Topic :: Utilities
Requires-Python: >=3.8
License-File: LICENSE
Requires-Dist: click<9.0,>=5.0
Requires-Dist: click-log<0.5.0,>=0.3.0
Requires-Dist: requests>=2.20.0
Requires-Dist: aiohttp<4.0.0,>=3.8.2
Requires-Dist: aiostream<0.8.0,>=0.4.3
Provides-Extra: google
Requires-Dist: aiohttp-oauthlib; extra == "google"
Provides-Extra: test
Requires-Dist: hypothesis<7.0.0,>=6.72.0; extra == "test"
Requires-Dist: pytest; extra == "test"
Requires-Dist: pytest-cov; extra == "test"
Requires-Dist: pytest-httpserver; extra == "test"
Requires-Dist: trustme; extra == "test"
Requires-Dist: pytest-asyncio; extra == "test"
Requires-Dist: aioresponses; extra == "test"
Dynamic: license-file
